ragstack_knowledge_graph/__init__.py
ragstack_knowledge_graph/cassandra_graph_store.py
ragstack_knowledge_graph/extraction.py
ragstack_knowledge_graph/knowledge_graph.py
ragstack_knowledge_graph/knowledge_schema.py
ragstack_knowledge_graph/prompt_templates/extraction.md
ragstack_knowledge_graph/prompt_templates/schema_inference.md
ragstack_knowledge_graph/py.typed
ragstack_knowledge_graph/render.py
ragstack_knowledge_graph/runnables.py
ragstack_knowledge_graph/schema_inference.py
ragstack_knowledge_graph/templates.py
ragstack_knowledge_graph/traverse.py
ragstack_knowledge_graph/utils.py
ragstack_ai_knowledge_graph-0.0.2.dist-info/METADATA
ragstack_ai_knowledge_graph-0.0.2.dist-info/WHEEL
ragstack_ai_knowledge_graph-0.0.2.dist-info/RECORD
